{
  "dataSetId": "6c7b2a6a-6ff0-11ef-a6d5-aa2a7e7a6271",
  "year": "2019",
  "category": "physics",
  "overallMotivation": "\"for contributions to our understanding of the evolution of the universe and Earth\u2019s place in the cosmos\"",
  "laureates": [
    {
      "id": "973",
      "firstname": "James",
      "surname": "Peebles",
      "motivation": "\"for theoretical discoveries in physical cosmology\"",
      "share": "2"
    },
    {
      "id": "974",
      "firstname": "Michel",
      "surname": "Mayor",
      "motivation": "\"for the discovery of an exoplanet orbiting a solar-type star\"",
      "share": "4"
    },
    {
      "id": "975",
      "firstname": "Didier",
      "surname": "Queloz",
      "motivation": "\"for the discovery of an exoplanet orbiting a solar-type star\"",
      "share": "4"
    }
  ]
}
